pret/ui/simple_dock/__init__.py
pret_simple_dock-0.2.2.data/data/share/jupyter/labextensions/react-simple-dock/package.json
pret_simple_dock-0.2.2.data/data/share/jupyter/labextensions/react-simple-dock/schemas/react-simple-dock/package.json.orig
pret_simple_dock-0.2.2.data/data/share/jupyter/labextensions/react-simple-dock/static/33.53f5e3ecdcb5899344ab.js
pret_simple_dock-0.2.2.data/data/share/jupyter/labextensions/react-simple-dock/static/33.53f5e3ecdcb5899344ab.js.LICENSE.txt
pret_simple_dock-0.2.2.data/data/share/jupyter/labextensions/react-simple-dock/static/443.d6535ee45ac3dceae37a.js
pret_simple_dock-0.2.2.data/data/share/jupyter/labextensions/react-simple-dock/static/577.57c28e69641a22688c4b.js
pret_simple_dock-0.2.2.data/data/share/jupyter/labextensions/react-simple-dock/static/848.0dd00f09c6e597805437.js
pret_simple_dock-0.2.2.data/data/share/jupyter/labextensions/react-simple-dock/static/848.0dd00f09c6e597805437.js.LICENSE.txt
pret_simple_dock-0.2.2.data/data/share/jupyter/labextensions/react-simple-dock/static/982.c8103f6d132d43c8db6d.js
pret_simple_dock-0.2.2.data/data/share/jupyter/labextensions/react-simple-dock/static/remoteEntry.6cc511d66c0bd4791764.js
pret_simple_dock-0.2.2.data/data/share/jupyter/labextensions/react-simple-dock/static/style.js
pret_simple_dock-0.2.2.data/data/share/jupyter/labextensions/react-simple-dock/static/third-party-licenses.json
pret_simple_dock-0.2.2.dist-info/METADATA
pret_simple_dock-0.2.2.dist-info/WHEEL
pret_simple_dock-0.2.2.dist-info/licenses/LICENSE
pret_simple_dock-0.2.2.dist-info/RECORD
