Metadata-Version: 2.4
Name: pret-simple-dock
Version: 0.2.2
Summary: Simple dock component for Pret
Project-URL: homepage, https://github.com/percevalw/react-simple-dock
Project-URL: repository, https://github.com/percevalw/react-simple-dock
Project-URL: documentation, https://percevalw.github.io/react-simple-dock
Author-email: Perceval Wajsbürt <perceval.wajsburt@gmail.com>
License:                                  Apache License
License-File: LICENSE
Requires-Python: <4.0,>=3.7
Requires-Dist: pret
Provides-Extra: dev
Requires-Dist: hatch-jupyter-builder; extra == 'dev'
Requires-Dist: hatchling; extra == 'dev'
